yieldcurve/__init__.py
yieldcurve/examples/demo.ipynb
yieldcurve/loader/__init__.py
yieldcurve/loader/fred_loader.py
yieldcurve/models/__init__.py
yieldcurve/models/nss.py
yieldcurve/models/spline.py
yieldcurve/plots/__init__.py
yieldcurve/plots/plot_curve.py
yieldcurve/utils/__init__.py
yieldcurve/utils/conversions.py
yieldcurve/utils/metrics.py
yieldcurve_analysis-0.1.0.dist-info/METADATA
yieldcurve_analysis-0.1.0.dist-info/WHEEL
yieldcurve_analysis-0.1.0.dist-info/top_level.txt
yieldcurve_analysis-0.1.0.dist-info/RECORD
