Metadata-Version: 2.4
Name: yieldcurve-analysis
Version: 0.1.0
Summary: A Python package for downloading US Treasury yields from FRED, fitting yield curve models, and performing analysis
Author: Yield Curve Analysis Team
License: MIT
Project-URL: Homepage, https://github.com/sinhaarya04/YieldCurve
Project-URL: Documentation, https://github.com/sinhaarya04/YieldCurve#readme
Project-URL: Repository, https://github.com/sinhaarya04/YieldCurve
Keywords: yield-curve,treasury,fred,nelson-siegel,spline,fixed-income,finance
Classifier: Development Status :: 4 - Beta
Classifier: Intended Audience :: Financial and Insurance Industry
Classifier: Intended Audience :: Science/Research
Classifier: License :: OSI Approved :: MIT License
Classifier: Programming Language :: Python :: 3
Classifier: Programming Language :: Python :: 3.7
Classifier: Programming Language :: Python :: 3.8
Classifier: Programming Language :: Python :: 3.9
Classifier: Programming Language :: Python :: 3.10
Classifier: Programming Language :: Python :: 3.11
Classifier: Topic :: Office/Business :: Financial
Classifier: Topic :: Scientific/Engineering :: Mathematics
Requires-Python: >=3.7
Requires-Dist: numpy>=1.19.0
Requires-Dist: scipy>=1.5.0
Requires-Dist: matplotlib>=3.3.0
Requires-Dist: requests>=2.24.0
Provides-Extra: dev
Requires-Dist: pytest>=6.0; extra == "dev"
Requires-Dist: black>=21.0; extra == "dev"
Requires-Dist: flake8>=3.8; extra == "dev"
Requires-Dist: mypy>=0.800; extra == "dev"
